nexmo/__init__.py
nexmo/_internal.py
nexmo/errors.py
nexmo/sms.py
nexmo/verify.py
nexmo/voice.py
nexmo-2.5.2.dist-info/LICENSE.txt
nexmo-2.5.2.dist-info/METADATA
nexmo-2.5.2.dist-info/WHEEL
nexmo-2.5.2.dist-info/top_level.txt
nexmo-2.5.2.dist-info/RECORD
