Metadata-Version: 2.1
Name: nexmo
Version: 2.5.2
Summary: Nexmo Client Library for Python
Home-page: https://github.com/Nexmo/nexmo-python
Author: Nexmo
Author-email: devrel@nexmo.com
License: MIT
Platform: any
Classifier: Programming Language :: Python
Classifier: Programming Language :: Python :: 3
Classifier: Programming Language :: Python :: 3.4
Classifier: Programming Language :: Python :: 3.5
Classifier: Programming Language :: Python :: 3.6
Classifier: Programming Language :: Python :: 3.7
Classifier: Programming Language :: Python :: 3.8
Requires-Python: >=3, !=3.0.*, !=3.1.*, !=3.2.*, !=3.3.*
